pyssa/__init__.py
pyssa/direct_naive.py
pyssa/pyssa.py
pyssa/pyssa_cython.c
pyssa/pyssa_numba.py
pyssa/results.py
pyssa/simulation.py
pyssa/utils.py
pyssa-0.5.4.dist-info/METADATA
pyssa-0.5.4.dist-info/RECORD
pyssa-0.5.4.dist-info/WHEEL
pyssa-0.5.4.dist-info/top_level.txt
