Metadata-Version: 2.1
Name: pyssa
Version: 0.5.4
Summary: Python package for stochastic simulations
Home-page: https://github.com/Heuro-labs/pyssa
Author: Dileep Kishore, Srikiran Chandrasekaran
Author-email: k.dileep1994@gmail.com
License: Apache Software License 2.0
Keywords: pyssa stochastic gillepsie simulation numba
Platform: UNKNOWN
Classifier: Development Status :: 4 - Beta
Classifier: Intended Audience :: Developers
Classifier: Intended Audience :: Science/Research
Classifier: License :: OSI Approved :: Apache Software License
Classifier: Natural Language :: English
Classifier: Programming Language :: Python :: 3.6
Classifier: Programming Language :: Python :: 3.7
Requires-Dist: numpy
Requires-Dist: numba
Requires-Dist: matplotlib
